[
  {"gbif":"6","premium":"2","pakke":"Fisk 1","art":"- Ukjent -","latin":"","slekt":"","familie":"","artsinfo":"","silhuett":"","farge":"","fremmedart":"","status":"","habitat":"ferskvann, saltvann, kyst","fylker":"","kjennetegn":"","lyd":"","notat":"","lengde":[0,10000],"hoyde":[0,0],"vekt":[0,0],"sesong":[0,0],"forekomst":7,"forekomst_tekst":"","lenke1":"","lenke2":"","lenke3":"","lenke4":"","lenke5":""},
  {"gbif":"8215487","premium":"2","pakke":"Fisk 1","art":"Ørret","latin":"Salmo trutta","slekt":"Salmo","familie":"Laksefamilien","artsinfo":"Kalles også bekke-/sjøørret, bleke, byrting, kjøe, kludd, kræde, sjøblanke og strending","silhuett":"Vanlig fisk","farge":"","fremmedart":"","status":"LC","habitat":"ferskvann","fylker":"","kjennetegn":"","lyd":"","notat":"","lengde":[0,100],"hoyde":[0,0],"vekt":[0,15000],"sesong":[0,0],"forekomst":7,"forekomst_tekst":"","lenke1":"https://snl.no/%C3%B8rret","lenke2":"https://no.wikipedia.org/wiki/%C3%98rret","lenke3":"https://www.artsdatabanken.no/taxon/Salmo%20trutta/42663","lenke4":"","lenke5":""},
  {"gbif":"8084280","premium":"2","pakke":"Fisk 1","art":"Torsk","latin":"Gadus morhua","slekt":"Gadus","familie":"Torskefamilien","artsinfo":"Kalles også gjedd, kysttorsk, loddetorsk, skrei og taretorsk","silhuett":"Vanlig fisk","farge":"","fremmedart":"","status":"LC","habitat":"saltvann","fylker":"","kjennetegn":"","lyd":"","notat":"","lengde":[0,0],"hoyde":[0,0],"vekt":[0,0],"sesong":[0,0],"forekomst":7,"forekomst_tekst":"","lenke1":"https://snl.no/torsk","lenke2":"https://no.wikipedia.org/wiki/Torsk","lenke3":"https://www.artsdatabanken.no/taxon/Gadus%20morhua/42798","lenke4":"","lenke5":""},
  {"gbif":"8140485","premium":"2","pakke":"Fisk 1","art":"Abbor","latin":"Perca fluviatilis","slekt":"Perca","familie":"Abborfamilien","artsinfo":"Kalles også skjebbe og tryte","silhuett":"Vanlig fisk","farge":"","fremmedart":"SE","status":"","habitat":"ferskvann","fylker":"","kjennetegn":"","lyd":"","notat":"","lengde":[0,0],"hoyde":[0,0],"vekt":[0,0],"sesong":[0,0],"forekomst":7,"forekomst_tekst":"","lenke1":"https://snl.no/abbor","lenke2":"https://no.wikipedia.org/wiki/Abbor","lenke3":"https://www.artsdatabanken.no/taxon/Perca%20fluviatilis/42983","lenke4":"","lenke5":""},
  {"gbif":"2415861","premium":"2","pakke":"Fisk 1","art":"Sei","latin":"Pollachius virens","slekt":"Pollachius","familie":"Torskefamilien","artsinfo":"Kalles også grønnspor, høling, klakkesei, kod, mort, pale, seikod og snadd","silhuett":"Vanlig fisk","farge":"","fremmedart":"","status":"LC","habitat":"saltvann","fylker":"","kjennetegn":"","lyd":"","notat":"","lengde":[0,0],"hoyde":[0,0],"vekt":[0,0],"sesong":[0,0],"forekomst":7,"forekomst_tekst":"","lenke1":"https://snl.no/sei","lenke2":"https://no.wikipedia.org/wiki/Sei","lenke3":"https://www.artsdatabanken.no/taxon/Pollachius%20virens/42807","lenke4":"","lenke5":""},
  {"gbif":"2415872","premium":"2","pakke":"Fisk 1","art":"Lyr","latin":"Pollachius pollachius","slekt":"Pollachius","familie":"Torskefamilien","artsinfo":"Kalles også bladlyr, lyrsei og lyrtorsk","silhuett":"Vanlig fisk","farge":"","fremmedart":"","status":"LC","habitat":"saltvann","fylker":"","kjennetegn":"","lyd":"","notat":"","lengde":[0,0],"hoyde":[0,0],"vekt":[0,0],"sesong":[0,0],"forekomst":7,"forekomst_tekst":"","lenke1":"https://snl.no/lyr","lenke2":"https://no.wikipedia.org/wiki/Lyr","lenke3":"https://www.artsdatabanken.no/taxon/Pollachius%20pollachius/42806","lenke4":"","lenke5":""},
  {"gbif":"2374149","premium":"2","pakke":"Fisk 1","art":"Makrell","latin":"Scomber scombrus","slekt":"Scomber","familie":"Makrellfamilien","artsinfo":"Kalles også bolt, geir, kuvl, pir, spir og stokkål","silhuett":"Vanlig fisk","farge":"","fremmedart":"","status":"LC","habitat":"saltvann","fylker":"","kjennetegn":"","lyd":"","notat":"","lengde":[0,0],"hoyde":[0,0],"vekt":[0,0],"sesong":[0,0],"forekomst":7,"forekomst_tekst":"","lenke1":"https://snl.no/makrell","lenke2":"https://no.wikipedia.org/wiki/Makrell","lenke3":"https://www.artsdatabanken.no/taxon/Scomber%20scombrus/43191","lenke4":"","lenke5":""},
  {"gbif":"2359706","premium":"2","pakke":"Fisk 1","art":"Mort","latin":"Rutilus rutilus","slekt":"Rutilus","familie":"Karpefamilien","artsinfo":"Kalles også flassrøye, raufjæring og sørrenne","silhuett":"Vanlig fisk","farge":"","fremmedart":"HI","status":"","habitat":"ferskvann","fylker":"","kjennetegn":"","lyd":"","notat":"","lengde":[0,0],"hoyde":[0,0],"vekt":[0,0],"sesong":[0,0],"forekomst":7,"forekomst_tekst":"","lenke1":"https://snl.no/mort","lenke2":"https://no.wikipedia.org/wiki/Mort","lenke3":"https://www.artsdatabanken.no/taxon/Rutilus%20rutilus/42631","lenke4":"","lenke5":""},
  {"gbif":"2346633","premium":"2","pakke":"Fisk 1","art":"Gjedde","latin":"Esox lucius","slekt":"Esox","familie":"Gjeddefamilien","artsinfo":"","silhuett":"Vanlig fisk","farge":"","fremmedart":"SE","status":"","habitat":"ferskvann","fylker":"","kjennetegn":"","lyd":"","notat":"","lengde":[0,0],"hoyde":[0,0],"vekt":[0,0],"sesong":[0,0],"forekomst":7,"forekomst_tekst":"","lenke1":"https://snl.no/gjedde","lenke2":"https://no.wikipedia.org/wiki/Gjedde","lenke3":"https://www.artsdatabanken.no/taxon/Esox%20lucius/42681","lenke4":"","lenke5":""},
  {"gbif":"2415788","premium":"2","pakke":"Fisk 1","art":"Hvitting","latin":"Merlangius merlangus","slekt":"Merlangius","familie":"Torskefamilien","artsinfo":"Kalles også bleke","silhuett":"Vanlig fisk","farge":"","fremmedart":"","status":"LC","habitat":"saltvann","fylker":"","kjennetegn":"","lyd":"","notat":"","lengde":[0,0],"hoyde":[0,0],"vekt":[0,0],"sesong":[0,0],"forekomst":6,"forekomst_tekst":"","lenke1":"https://no.wikipedia.org/wiki/Hvitting","lenke2":"https://no.wikipedia.org/wiki/Hvitting","lenke3":"https://www.artsdatabanken.no/taxon/Merlangius%20merlangus/42802","lenke4":"","lenke5":""},
  {"gbif":"2383163","premium":"1","pakke":"Fisk 2","art":"Bergnebb","latin":"Ctenolabrus rupestris","slekt":"Ctenolabrus","familie":"Leppefiskfamilien","artsinfo":"Kalles også berse, harjåd, råte, stinte og strikjette","silhuett":"Vanlig fisk","farge":"","fremmedart":"","status":"LC","habitat":"saltvann","fylker":"","kjennetegn":"","lyd":"","notat":"","lengde":[0,0],"hoyde":[0,0],"vekt":[0,0],"sesong":[0,0],"forekomst":6,"forekomst_tekst":"","lenke1":"https://snl.no/bergnebb","lenke2":"https://no.wikipedia.org/wiki/Bergnebb","lenke3":"https://www.artsdatabanken.no/taxon/Ctenolabrus%20rupestris/43042","lenke4":"","lenke5":""},
  {"gbif":"5212973","premium":"2","pakke":"Fisk 1","art":"Ål","latin":"Anguilla anguilla","slekt":"Anguilla","familie":"Ålefamilien","artsinfo":"","silhuett":"Ligner ål","farge":"","fremmedart":"","status":"EN","habitat":"saltvann","fylker":"","kjennetegn":"","lyd":"","notat":"","lengde":[0,0],"hoyde":[0,0],"vekt":[0,0],"sesong":[0,0],"forekomst":6,"forekomst_tekst":"","lenke1":"https://snl.no/%C3%A5l","lenke2":"https://no.wikipedia.org/wiki/%C3%85l_(fisk)","lenke3":"https://www.artsdatabanken.no/taxon/Anguilla%20anguilla/42580","lenke4":"","lenke5":""},
  {"gbif":"2383624","premium":"1","pakke":"Fisk 2","art":"Berggylte","latin":"Labrus bergylta","slekt":"Labrus","familie":"Leppefiskfamilien","artsinfo":"Kalles også berggylt, bergskjebbe og bergsugge","silhuett":"Vanlig fisk","farge":"","fremmedart":"","status":"LC","habitat":"saltvann","fylker":"","kjennetegn":"","lyd":"","notat":"","lengde":[0,0],"hoyde":[0,0],"vekt":[0,0],"sesong":[0,0],"forekomst":6,"forekomst_tekst":"","lenke1":"https://snl.no/berggylt","lenke2":"https://no.wikipedia.org/wiki/Berggylt","lenke3":"https://www.artsdatabanken.no/taxon/Labrus%20bergylta/43034","lenke4":"","lenke5":""},
  {"gbif":"2383649","premium":"1","pakke":"Fisk 2","art":"Blåstål","latin":"Labrus mixtus","slekt":"","familie":"Leppefiskfamilien","artsinfo":"Kalles også blåskål, blåskår og rødnebb","silhuett":"Vanlig fisk","farge":"","fremmedart":"","status":"LC","habitat":"saltvann","fylker":"","kjennetegn":"","lyd":"","notat":"","lengde":[0,0],"hoyde":[0,0],"vekt":[0,0],"sesong":[0,0],"forekomst":6,"forekomst_tekst":"","lenke1":"https://snl.no/bl%C3%A5st%C3%A5l","lenke2":"https://no.wikipedia.org/wiki/Bl%C3%A5st%C3%A5l","lenke3":"https://www.artsdatabanken.no/taxon/Labrus%20mixtus/43035","lenke4":"","lenke5":""},
  {"gbif":"2415906","premium":"1","pakke":"Fisk 2","art":"Sypike","latin":"Trisopterus minutus","slekt":"","familie":"Torskefamilien","artsinfo":"Kalles også kolge og kolje","silhuett":"Vanlig fisk","farge":"","fremmedart":"","status":"LC","habitat":"saltvann","fylker":"","kjennetegn":"","lyd":"","notat":"","lengde":[0,0],"hoyde":[0,0],"vekt":[0,0],"sesong":[0,0],"forekomst":6,"forekomst_tekst":"","lenke1":"https://snl.no/sypike","lenke2":"https://no.wikipedia.org/wiki/Sypike","lenke3":"https://www.artsdatabanken.no/taxon/Trisopterus%20minutus/42813","lenke4":"","lenke5":""},
  {"gbif":"2333785","premium":"1","pakke":"Fisk 2","art":"Vanlig ulke","latin":"Myoxocephalus scorpius","slekt":"","familie":"Ulkefamilien","artsinfo":"Kalles også marulk, pelekunter, pillekunter og ulke","silhuett":"Vanlig fisk","farge":"","fremmedart":"","status":"LC","habitat":"saltvann","fylker":"","kjennetegn":"","lyd":"","notat":"","lengde":[0,0],"hoyde":[0,0],"vekt":[0,0],"sesong":[0,0],"forekomst":6,"forekomst_tekst":"","lenke1":"https://snl.no/vanlig_ulke","lenke2":"https://no.wikipedia.org/wiki/Vanlig_ulke","lenke3":"https://www.artsdatabanken.no/taxon/Myoxocephalus%20scorpius/42911","lenke4":"","lenke5":""},
  {"gbif":"5213960","premium":"1","pakke":"Fisk 2","art":"Sandflyndre","latin":"Limanda limanda","slekt":"","familie":"Flyndrefamilien","artsinfo":"Kalles også sandskrå og sandskrubbe","silhuett":"Flat fisk","farge":"","fremmedart":"","status":"LC","habitat":"saltvann","fylker":"","kjennetegn":"","lyd":"","notat":"","lengde":[0,0],"hoyde":[0,0],"vekt":[0,0],"sesong":[0,0],"forekomst":6,"forekomst_tekst":"","lenke1":"https://snl.no/sandflyndre","lenke2":"https://no.wikipedia.org/wiki/Sandflyndre","lenke3":"https://www.artsdatabanken.no/taxon/Limanda%20limanda/43237","lenke4":"","lenke5":""},
  {"gbif":"4284021","premium":"1","pakke":"Fisk 2","art":"Røye","latin":"Salvelinus alpinus","slekt":"","familie":"Laksefamilien","artsinfo":"Kalles også bleke, gautefisk, gib, kolmule, kolmunn, røe, rør, sjørøye, stilk, storrøye og vassrør","silhuett":"Vanlig fisk","farge":"","fremmedart":"","status":"LC","habitat":"ferskvann","fylker":"","kjennetegn":"","lyd":"","notat":"","lengde":[0,0],"hoyde":[0,0],"vekt":[0,0],"sesong":[0,0],"forekomst":6,"forekomst_tekst":"","lenke1":"https://snl.no/r%C3%B8ye","lenke2":"https://no.wikipedia.org/wiki/R%C3%B8ye","lenke3":"https://www.artsdatabanken.no/taxon/Salvelinus%20alpinus/42665","lenke4":"","lenke5":""},
  {"gbif":"4286327","premium":"1","pakke":"Fisk 2","art":"Trepigget stingsild","latin":"Gasterosteus aculeatus","slekt":"","familie":"Stingsildfamilien","artsinfo":"Kalles også benten, hønnsik, hønnsild, hønntju, hornsyle, hundstikke, stegg, stengsild, stensild, stikkfisk, stikksild og stikling","silhuett":"Vanlig fisk","farge":"","fremmedart":"","status":"LC","habitat":"ferskvann, saltvann, kyst","fylker":"","kjennetegn":"","lyd":"","notat":"","lengde":[0,0],"hoyde":[0,0],"vekt":[0,0],"sesong":[0,0],"forekomst":6,"forekomst_tekst":"","lenke1":"https://snl.no/trepigget_stingsild","lenke2":"https://no.wikipedia.org/wiki/Trepigget_stingsild","lenke3":"https://www.artsdatabanken.no/taxon/Gasterosteus%20aculeatus/42850","lenke4":"","lenke5":""},
  {"gbif":"2409330","premium":"1","pakke":"Fisk 2","art":"Skrubbe","latin":"Platichthys flesus","slekt":"","familie":"Flyndrefamilien","artsinfo":"Kalles også skrubbeflyndre","silhuett":"Flat fisk","farge":"","fremmedart":"","status":"LC","habitat":"saltvann","fylker":"","kjennetegn":"","lyd":"","notat":"","lengde":[0,0],"hoyde":[0,0],"vekt":[0,0],"sesong":[0,0],"forekomst":6,"forekomst_tekst":"","lenke1":"https://snl.no/skrubbe","lenke2":"https://no.wikipedia.org/wiki/Skrubbe","lenke3":"https://www.artsdatabanken.no/taxon/Platichthys%20flesus/43239","lenke4":"","lenke5":""},
  {"gbif":"5214880","premium":"1","pakke":"Fisk 2","art":"Lange","latin":"Molva molva","slekt":"","familie":"Torskefamilien","artsinfo":"","silhuett":"Vanlig fisk","farge":"","fremmedart":"","status":"LC","habitat":"saltvann","fylker":"","kjennetegn":"","lyd":"","notat":"","lengde":[0,0],"hoyde":[0,0],"vekt":[0,0],"sesong":[0,0],"forekomst":6,"forekomst_tekst":"","lenke1":"https://snl.no/lange","lenke2":"https://no.wikipedia.org/wiki/Lange","lenke3":"https://www.artsdatabanken.no/taxon/Molva%20molva/42783","lenke4":"","lenke5":""},
  {"gbif":"2415822","premium":"1","pakke":"Fisk 2","art":"Hyse","latin":"Melanogrammus aeglefinus","slekt":"","familie":"Torskefamilien","artsinfo":"Kalles også kolje","silhuett":"Vanlig fisk","farge":"","fremmedart":"","status":"LC","habitat":"saltvann","fylker":"","kjennetegn":"","lyd":"","notat":"","lengde":[0,0],"hoyde":[0,0],"vekt":[0,0],"sesong":[0,0],"forekomst":6,"forekomst_tekst":"","lenke1":"https://snl.no/hyse","lenke2":"https://no.wikipedia.org/wiki/Hyse","lenke3":"https://www.artsdatabanken.no/taxon/Melanogrammus%20aeglefinus/42800","lenke4":"","lenke5":""},
  {"gbif":"7700106","premium":"1","pakke":"Fisk 2","art":"Rødspette","latin":"Pleuronectes platessa","slekt":"","familie":"Flyndrefamilien","artsinfo":"Kalles også flyndre, gullflyndre og kongeflyndre","silhuett":"Flat fisk","farge":"","fremmedart":"","status":"LC","habitat":"saltvann","fylker":"","kjennetegn":"","lyd":"","notat":"","lengde":[0,0],"hoyde":[0,0],"vekt":[0,0],"sesong":[0,0],"forekomst":6,"forekomst_tekst":"","lenke1":"https://snl.no/r%C3%B8dspette","lenke2":"https://no.wikipedia.org/wiki/R%C3%B8dspette","lenke3":"https://www.artsdatabanken.no/taxon/Pleuronectes%20platessa/43235","lenke4":"","lenke5":""},
  {"gbif":"9809222","premium":"1","pakke":"Fisk 2","art":"Brasme","latin":"Abramis brama","slekt":"","familie":"Karpefamilien","artsinfo":"Kalles også brase og brasp","silhuett":"Vanlig fisk","farge":"","fremmedart":"","status":"LC","habitat":"ferskvann","fylker":"","kjennetegn":"","lyd":"","notat":"","lengde":[0,0],"hoyde":[0,0],"vekt":[0,0],"sesong":[0,0],"forekomst":6,"forekomst_tekst":"","lenke1":"https://snl.no/brasme","lenke2":"https://no.wikipedia.org/wiki/Brasme","lenke3":"https://www.artsdatabanken.no/taxon/Abramis%20brama/42613","lenke4":"","lenke5":""},
  {"gbif":"2336597","premium":"1","pakke":"Fisk 2","art":"Knurr","latin":"Eutrigla gurnardus","slekt":"","familie":"Knurrfamilien","artsinfo":"Kalles også gråknurr, prest, rinald, ryt, snork og svintryt","silhuett":"Vanlig fisk","farge":"","fremmedart":"","status":"LC","habitat":"saltvann","fylker":"","kjennetegn":"","lyd":"","notat":"","lengde":[0,0],"hoyde":[0,0],"vekt":[0,0],"sesong":[0,0],"forekomst":6,"forekomst_tekst":"","lenke1":"https://snl.no/knurr","lenke2":"https://no.wikipedia.org/wiki/Knurr","lenke3":"https://www.artsdatabanken.no/taxon/Eutrigla%20gurnardus/42884","lenke4":"","lenke5":""},
  {"gbif":"2375526","premium":"1","pakke":"Fisk 2","art":"Svartkutling","latin":"Gobius niger","slekt":"","familie":"Kutlingfamilien","artsinfo":"Kalles også bånnulke","silhuett":"Vanlig fisk","farge":"","fremmedart":"","status":"LC","habitat":"saltvann","fylker":"","kjennetegn":"","lyd":"","notat":"","lengde":[0,0],"hoyde":[0,0],"vekt":[0,0],"sesong":[0,0],"forekomst":6,"forekomst_tekst":"","lenke1":"https://snl.no/svartkutling","lenke2":"https://no.wikipedia.org/wiki/Svartkutling","lenke3":"https://www.artsdatabanken.no/taxon/Gobius%20niger/43159","lenke4":"","lenke5":""},
  {"gbif":"11003421","premium":"1","pakke":"Fisk 2","art":"Tangkutling","latin":"Pomatoschistus flavescens","slekt":"","familie":"Kutlingfamilien","artsinfo":"","silhuett":"Vanlig fisk","farge":"","fremmedart":"","status":"LC","habitat":"saltvann","fylker":"","kjennetegn":"","lyd":"","notat":"","lengde":[0,0],"hoyde":[0,0],"vekt":[0,0],"sesong":[0,0],"forekomst":5,"forekomst_tekst":"","lenke1":"https://snl.no/tangkutling","lenke2":"https://no.wikipedia.org/wiki/Tangkutling","lenke3":"https://www.artsdatabanken.no/taxon/Pomatoschistus%20flavescens/187054","lenke4":"","lenke5":""},
  {"gbif":"7595433","premium":"1","pakke":"Fisk 2","art":"Laks","latin":"Salmo salar","slekt":"","familie":"Laksefamilien","artsinfo":"Kalles også blege, diddi, grilse, leksing, namsblank, parr, pjakk, småblank, smolt, svele, svidde og tert","silhuett":"Vanlig fisk","farge":"","fremmedart":"","status":"NT","habitat":"ferskvann","fylker":"","kjennetegn":"","lyd":"","notat":"","lengde":[0,0],"hoyde":[0,0],"vekt":[0,0],"sesong":[0,0],"forekomst":5,"forekomst_tekst":"","lenke1":"https://snl.no/laks","lenke2":"https://no.wikipedia.org/wiki/Laks","lenke3":"https://www.artsdatabanken.no/taxon/Salmo%20salar/42662","lenke4":"","lenke5":""},
  {"gbif":"4409653","premium":"1","pakke":"Fisk 2","art":"Ørekyt","latin":"Phoxinus phoxinus","slekt":"","familie":"Karpefamilien","artsinfo":"Kalles også åkyte, ålekue, blindsild, goløye, gørkyte, gorsild, kime, pøyt og simen","silhuett":"Vanlig fisk","farge":"","fremmedart":"SE","status":"","habitat":"saltvann","fylker":"","kjennetegn":"","lyd":"","notat":"","lengde":[0,0],"hoyde":[0,0],"vekt":[0,0],"sesong":[0,0],"forekomst":5,"forekomst_tekst":"","lenke1":"https://snl.no/%C3%B8rekyt","lenke2":"https://no.wikipedia.org/wiki/%C3%98rekyt","lenke3":"https://www.artsdatabanken.no/taxon/Phoxinus%20phoxinus/42635","lenke4":"","lenke5":""},
  {"gbif":"2362635","premium":"1","pakke":"Fisk 2","art":"Sørv","latin":"Scardinius erythrophthalmus","slekt":"","familie":"Karpefamilien","artsinfo":"Kalles også flossmort, planke, plunke, sørje, sorv, syrje og syrril","silhuett":"Vanlig fisk","farge":"","fremmedart":"SE","status":"","habitat":"ferskvann","fylker":"","kjennetegn":"","lyd":"","notat":"","lengde":[0,0],"hoyde":[0,0],"vekt":[0,0],"sesong":[0,0],"forekomst":5,"forekomst_tekst":"","lenke1":"https://snl.no/s%C3%B8rv","lenke2":"https://no.wikipedia.org/wiki/S%C3%B8rv","lenke3":"https://www.artsdatabanken.no/taxon/Scardinius%20erythrophthalmus/42633","lenke4":"","lenke5":""},
  {"gbif":"2362925","premium":"1","pakke":"Fisk 2","art":"Laue","latin":"Alburnus alburnus","slekt":"","familie":"Karpefamilien","artsinfo":"Kalles også løve, løye og prit","silhuett":"Vanlig fisk","farge":"","fremmedart":"","status":"LC","habitat":"ferskvann","fylker":"","kjennetegn":"","lyd":"","notat":"","lengde":[0,0],"hoyde":[0,0],"vekt":[0,0],"sesong":[0,0],"forekomst":5,"forekomst_tekst":"","lenke1":"https://snl.no/laue","lenke2":"https://no.wikipedia.org/wiki/Laue","lenke3":"https://www.artsdatabanken.no/taxon/Alburnus%20alburnus/42621","lenke4":"","lenke5":""},
  {"gbif":"5210421","premium":"1","pakke":"Fisk 2","art":"Tangsprell","latin":"Pholis gunnellus","slekt":"","familie":"Tangsprellfamilien","artsinfo":"Kalles også teistefisk","silhuett":"Ligner ål","farge":"","fremmedart":"","status":"LC","habitat":"saltvann","fylker":"","kjennetegn":"","lyd":"","notat":"","lengde":[0,0],"hoyde":[0,0],"vekt":[0,0],"sesong":[0,0],"forekomst":5,"forekomst_tekst":"","lenke1":"https://snl.no/tangsprell","lenke2":"https://no.wikipedia.org/wiki/Tangsprell","lenke3":"https://www.artsdatabanken.no/taxon/Pholis%20gunnellus/43097","lenke4":"","lenke5":""},
  {"gbif":"8351946","premium":"1","pakke":"Fisk 2","art":"Sild","latin":"Clupea harengus","slekt":"","familie":"Sildefamilien","artsinfo":"Kalles også bladsild, feitsild og mussa","silhuett":"Vanlig fisk","farge":"","fremmedart":"","status":"LC","habitat":"saltvann","fylker":"","kjennetegn":"","lyd":"","notat":"","lengde":[0,0],"hoyde":[0,0],"vekt":[0,0],"sesong":[0,0],"forekomst":5,"forekomst_tekst":"","lenke1":"https://snl.no/sild","lenke2":"https://no.wikipedia.org/wiki/Sild","lenke3":"https://www.artsdatabanken.no/taxon/Clupea%20harengus/42596","lenke4":"","lenke5":""},
  {"gbif":"5962255","premium":"1","pakke":"Fisk 2","art":"Rognkjeks","latin":"Cyclopterus lumpus","slekt":"","familie":"Rognkjeksfamilien","artsinfo":"Kalles også rognkall, rognkylsa og steinbit","silhuett":"Vanlig fisk","farge":"","fremmedart":"","status":"LC","habitat":"saltvann","fylker":"","kjennetegn":"","lyd":"","notat":"","lengde":[0,0],"hoyde":[0,0],"vekt":[0,0],"sesong":[0,0],"forekomst":5,"forekomst_tekst":"","lenke1":"https://snl.no/rognkjeks","lenke2":"https://no.wikipedia.org/wiki/Rognkjeks","lenke3":"https://www.artsdatabanken.no/taxon/Cyclopterus%20lumpus/42937","lenke4":"","lenke5":""},
  {"gbif":"2383978","premium":"1","pakke":"Fisk 2","art":"Grønngylte","latin":"Symphodus melops","slekt":"","familie":"Leppefiskfamilien","artsinfo":"Kalles også grønngylt og helleskitt","silhuett":"Vanlig fisk","farge":"","fremmedart":"","status":"LC","habitat":"saltvann","fylker":"","kjennetegn":"","lyd":"","notat":"","lengde":[0,0],"hoyde":[0,0],"vekt":[0,0],"sesong":[0,0],"forekomst":5,"forekomst_tekst":"","lenke1":"https://snl.no/gr%C3%B8nngylt","lenke2":"https://no.wikipedia.org/wiki/Gr%C3%B8nngylt","lenke3":"https://www.artsdatabanken.no/taxon/Symphodus%20melops/43044","lenke4":"","lenke5":""},
  {"gbif":"4409643","premium":"1","pakke":"Fisk 2","art":"Vederbuk","latin":"Leuciscus idus","slekt":"","familie":"Karpefamilien","artsinfo":"Kalles også årbuk, gullvederbuk, hersing, hisling, id og raufjæring","silhuett":"Vanlig fisk","farge":"","fremmedart":"HI","status":"","habitat":"ferskvann","fylker":"","kjennetegn":"","lyd":"","notat":"","lengde":[0,0],"hoyde":[0,0],"vekt":[0,0],"sesong":[0,0],"forekomst":5,"forekomst_tekst":"","lenke1":"https://snl.no/vederbuk","lenke2":"https://no.wikipedia.org/wiki/Vederbuk","lenke3":"https://www.artsdatabanken.no/taxon/Leuciscus%20idus/42628","lenke4":"","lenke5":""},
  {"gbif":"2369178","premium":"1","pakke":"Fisk 2","art":"Horngjel","latin":"Belone belone","slekt":"","familie":"Horngjelfamilien","artsinfo":"Kalles også hornfisk, horngeir og nebbsild","silhuett":"Ligner ål","farge":"","fremmedart":"","status":"LC","habitat":"saltvann","fylker":"","kjennetegn":"","lyd":"","notat":"","lengde":[0,0],"hoyde":[0,0],"vekt":[0,0],"sesong":[0,0],"forekomst":5,"forekomst_tekst":"","lenke1":"https://snl.no/horngjel","lenke2":"https://no.wikipedia.org/wiki/Horngjel","lenke3":"https://www.artsdatabanken.no/taxon/Belone%20belone/42841","lenke4":"","lenke5":""},
  {"gbif":"2334227","premium":"1","pakke":"Fisk 2","art":"Dvergulke","latin":"Taurulus bubalis","slekt":"","familie":"Ulkefamilien","artsinfo":"","silhuett":"Vanlig fisk","farge":"","fremmedart":"","status":"LC","habitat":"saltvann","fylker":"","kjennetegn":"","lyd":"","notat":"","lengde":[0,17],"hoyde":[0,0],"vekt":[0,0],"sesong":[0,0],"forekomst":5,"forekomst_tekst":"","lenke1":"https://snl.no/dvergulke","lenke2":"https://no.wikipedia.org/wiki/Dvergulke","lenke3":"https://www.artsdatabanken.no/taxon/Taurulus%20bubalis/42914","lenke4":"","lenke5":""},
  {"gbif":"2359471","premium":"1","pakke":"Fisk 2","art":"Flire","latin":"Blicca bjoerkna","slekt":"","familie":"Karpefamilien","artsinfo":"Kalles også sørv","silhuett":"Vanlig fisk","farge":"","fremmedart":"SE","status":"","habitat":"ferskvann","fylker":"","kjennetegn":"","lyd":"","notat":"","lengde":[0,0],"hoyde":[0,0],"vekt":[0,0],"sesong":[0,0],"forekomst":5,"forekomst_tekst":"","lenke1":"https://snl.no/flire","lenke2":"https://no.wikipedia.org/wiki/Flire","lenke3":"https://www.artsdatabanken.no/taxon/Blicca%20bjoerkna/42615","lenke4":"","lenke5":""},
  {"gbif":"2415460","premium":"1","pakke":"Fisk 2","art":"Lake","latin":"Lota lota","slekt":"","familie":"Torskefamilien","artsinfo":"","silhuett":"Vanlig fisk","farge":"","fremmedart":"","status":"LC","habitat":"ferskvann","fylker":"","kjennetegn":"","lyd":"","notat":"","lengde":[0,0],"hoyde":[0,0],"vekt":[0,0],"sesong":[0,0],"forekomst":5,"forekomst_tekst":"","lenke1":"https://snl.no/lake_-_fiskeart","lenke2":"https://no.wikipedia.org/wiki/Lake_(fisk)","lenke3":"https://www.artsdatabanken.no/taxon/Lota%20lota/42788","lenke4":"","lenke5":""},
  {"gbif":"2379300","premium":"1","pakke":"Fisk 2","art":"Sandkutling","latin":"Pomatoschistus minutus","slekt":"","familie":"Kutlingfamilien","artsinfo":"","silhuett":"Vanlig fisk","farge":"","fremmedart":"","status":"LC","habitat":"saltvann","fylker":"","kjennetegn":"","lyd":"","notat":"","lengde":[0,0],"hoyde":[0,0],"vekt":[0,0],"sesong":[0,0],"forekomst":5,"forekomst_tekst":"","lenke1":"https://snl.no/sandkutling","lenke2":"https://no.wikipedia.org/wiki/Sandkutling","lenke3":"https://www.artsdatabanken.no/taxon/Pomatoschistus%20minutus/43155","lenke4":"","lenke5":""},
  {"gbif":"5215626","premium":"1","pakke":"Fisk 2","art":"Hågjel","latin":"Galeus melastomus","slekt":"","familie":"Rødhaifamilien","artsinfo":"","silhuett":"Hailignende","farge":"","fremmedart":"","status":"LC","habitat":"saltvann","fylker":"","kjennetegn":"","lyd":"","notat":"","lengde":[0,0],"hoyde":[0,0],"vekt":[0,0],"sesong":[0,0],"forekomst":5,"forekomst_tekst":"","lenke1":"https://snl.no/h%C3%A5gjel","lenke2":"https://no.wikipedia.org/wiki/H%C3%A5gjel","lenke3":"https://www.artsdatabanken.no/taxon/Galeus%20melastomus/42472","lenke4":"","lenke5":""},
  {"gbif":"5214022","premium":"1","pakke":"Fisk 2","art":"Lomre","latin":"Microstomus kitt","slekt":"","familie":"Flyndrefamilien","artsinfo":"Kalles også bergflyndre, landtunge, oterflyndre og rødtunge","silhuett":"Vanlig fisk","farge":"","fremmedart":"","status":"LC","habitat":"saltvann","fylker":"","kjennetegn":"","lyd":"","notat":"","lengde":[0,65],"hoyde":[0,0],"vekt":[0,0],"sesong":[0,0],"forekomst":5,"forekomst_tekst":"","lenke1":"https://snl.no/lomre","lenke2":"https://no.wikipedia.org/wiki/Lomre","lenke3":"https://www.artsdatabanken.no/taxon/Microstomus%20kitt/43241","lenke4":"","lenke5":""},
  {"gbif":"5207464","premium":"1","pakke":"Fisk 2","art":"Stam","latin":"Leuciscus cephalus","slekt":"","familie":"Karpefamilien","artsinfo":"Kalles også årbuk og skal","silhuett":"Vanlig fisk","farge":"","fremmedart":"","status":"LC","habitat":"ferskvann","fylker":"","kjennetegn":"","lyd":"","notat":"","lengde":[0,80],"hoyde":[0,0],"vekt":[0,3500],"sesong":[0,0],"forekomst":5,"forekomst_tekst":"","lenke1":"https://snl.no/stam","lenke2":"https://no.wikipedia.org/wiki/Stam","lenke3":"https://www.artsdatabanken.no/taxon/Leuciscus%20cephalus/42627","lenke4":"","lenke5":""},
  {"gbif":"5216368","premium":"1","pakke":"Fisk 2","art":"Pigghå","latin":"Squalus acanthias","slekt":"","familie":"Pigghåfamilien","artsinfo":"Kalles også blankhå og hå","silhuett":"Ligner hai","farge":"","fremmedart":"","status":"VU","habitat":"saltvann","fylker":"","kjennetegn":"","lyd":"","notat":"","lengde":[20,120],"hoyde":[0,0],"vekt":[0,9000],"sesong":[0,0],"forekomst":5,"forekomst_tekst":"","lenke1":"https://snl.no/piggh%C3%A5","lenke2":"https://no.wikipedia.org/wiki/Piggh%C3%A5","lenke3":"https://www.artsdatabanken.no/taxon/Squalus%20acanthias/42512","lenke4":"","lenke5":""},
  {"gbif":"2409218","premium":"1","pakke":"Fisk 2","art":"Kveite","latin":"Hippoglossus hippoglossus","slekt":"","familie":"Flyndrefamilien","artsinfo":"Kalles også hellefisk, helleflyndre, kveitebarn og storkveite","silhuett":"Vanlig fisk","farge":"","fremmedart":"","status":"LC","habitat":"saltvann","fylker":"","kjennetegn":"","lyd":"","notat":"","lengde":[0,300],"hoyde":[0,0],"vekt":[0,300000],"sesong":[0,0],"forekomst":5,"forekomst_tekst":"","lenke1":"https://snl.no/kveite","lenke2":"https://no.wikipedia.org/wiki/Kveite","lenke3":"https://www.artsdatabanken.no/taxon/Hippoglossus%20hippoglossus/43249","lenke4":"","lenke5":""},
  {"gbif":"2335390","premium":"1","pakke":"Fisk 2","art":"Lusuer","latin":"Sebastes viviparus","slekt":"","familie":"Uerfamilien","artsinfo":"Kalles også småuer","silhuett":"Vanlig fisk","farge":"","fremmedart":"","status":"LC","habitat":"saltvann","fylker":"","kjennetegn":"","lyd":"","notat":"","lengde":[0,35],"hoyde":[0,0],"vekt":[0,0],"sesong":[0,0],"forekomst":5,"forekomst_tekst":"","lenke1":"https://snl.no/lusuer","lenke2":"https://no.wikipedia.org/wiki/Lusuer","lenke3":"https://www.artsdatabanken.no/taxon/Sebastes%20viviparus/42879","lenke4":"","lenke5":""},
  {"gbif":"2415505","premium":"1","pakke":"Fisk 2","art":"Brosme","latin":"Brosme brosme","slekt":"","familie":"Torskefamilien","artsinfo":"","silhuett":"Vanlig fisk","farge":"","fremmedart":"","status":"LC","habitat":"saltvann","fylker":"","kjennetegn":"","lyd":"","notat":"","lengde":[0,100],"hoyde":[0,0],"vekt":[0,15000],"sesong":[0,0],"forekomst":5,"forekomst_tekst":"","lenke1":"https://snl.no/brosme","lenke2":"https://no.wikipedia.org/wiki/Brosme","lenke3":"https://www.artsdatabanken.no/taxon/Brosme%20brosme/42781","lenke4":"","lenke5":""}
]

